{"is_source_file": true, "file_id": 13, "git_revision": "", "state": 1, "description": "", "external_files": [], "external_methods": [], "published": [], "classes": [], "methods": [], "calls": [], "search-terms": [], "ctags": [{"_type": "tag", "name": "connectMongo", "path": "/home/kavia/workspace/code-generation/hello-world-api-7161-7170/api_backend/src/db/mongoose.js", "pattern": "/^  connectMongo,$/", "language": "JavaScript", "kind": "field", "scope": "module.exports", "scopeKind": "class"}, {"_type": "tag", "name": "connectMongo", "path": "/home/kavia/workspace/code-generation/hello-world-api-7161-7170/api_backend/src/db/mongoose.js", "pattern": "/^async function connectMongo() {$/", "language": "JavaScript", "kind": "function", "signature": "()"}, {"_type": "tag", "name": "mongoose", "path": "/home/kavia/workspace/code-generation/hello-world-api-7161-7170/api_backend/src/db/mongoose.js", "pattern": "/^const mongoose = require('mongoose');$/", "language": "JavaScript", "kind": "constant"}], "format": "JavaScript", "hash": "d825ee67469ee0f582fbd3abfd47b450", "format-version": 4, "code-base-name": "api_backend", "filename": "api_backend/src/db/mongoose.js", "knowledge_revision": 26}